.gitignore
AUTHORS
LICENSE
MANIFEST
README.md
setup.py
deploy/app.iss
deploy/app.py
deploy/setup.py
deploy/wallaby.icns
deploy/wallaby.ico
wallaby/__init__.py
wallaby/apps/__init__.py
wallaby/apps/crm/UI_mainWindow.py
wallaby/apps/crm/__init__.py
wallaby/apps/crm/mainWindow.py
wallaby/apps/crm/mainWindow.ui
wallaby/apps/crm/couchapp/.couchappignore
wallaby/apps/crm/couchapp/.couchapprc
wallaby/apps/crm/couchapp/_docs/WallabyApp2.json
wallaby/apps/crm/couchapp/_docs/company.json
wallaby/apps/crm/couchapp/_docs/contactTypes.json
wallaby/apps/crm/couchapp/_docs/counties.json
wallaby/apps/crm/couchapp/_docs/countries.json
wallaby/apps/crm/couchapp/_docs/numbers.json
wallaby/apps/crm/couchapp/_docs/units.json
wallaby/apps/crm/couchapp/filters/all.js
wallaby/apps/crm/couchapp/filters/articles.js
wallaby/apps/crm/couchapp/filters/customers.js
wallaby/apps/crm/couchapp/filters/invoices.js
wallaby/apps/crm/couchapp/views/CAOCustomers/map.js
wallaby/apps/crm/couchapp/views/CAODocs/map.js
wallaby/apps/crm/couchapp/views/InvoiceGenerationErrors/map.js
wallaby/apps/crm/couchapp/views/allContracts/map.js
wallaby/apps/crm/couchapp/views/allContractsByNextinvoice/map.js
wallaby/apps/crm/couchapp/views/allDueContracts/map.js
wallaby/apps/crm/couchapp/views/allInvoices/map.js
wallaby/apps/crm/couchapp/views/allInvoices/reduce.js
wallaby/apps/crm/couchapp/views/allInvoicesByInvoicedate/map.js
wallaby/apps/crm/couchapp/views/allInvoicesByInvoicedate/reduce.js
wallaby/apps/crm/couchapp/views/allInvoicesByStatus/map.js
wallaby/apps/crm/couchapp/views/allInvoicesByStatus/reduce.js
wallaby/apps/crm/couchapp/views/articleInvoices/map.js
wallaby/apps/crm/couchapp/views/articles/map.js
wallaby/apps/crm/couchapp/views/conflicts/map.js
wallaby/apps/crm/couchapp/views/customerContracts/map.js
wallaby/apps/crm/couchapp/views/customerInvoices/map.js
wallaby/apps/crm/couchapp/views/customerInvoices/reduce.js
wallaby/apps/crm/couchapp/views/customerInvoicesByInvoicedate/map.js
wallaby_app_crm.egg-info/PKG-INFO
wallaby_app_crm.egg-info/SOURCES.txt
wallaby_app_crm.egg-info/dependency_links.txt
wallaby_app_crm.egg-info/requires.txt
wallaby_app_crm.egg-info/top_level.txt